KangRollGeneCancer/__init__.py
KangRollGeneCancer/analyze_gene.py
KangRollGeneCancer-0.4.dist-info/METADATA
KangRollGeneCancer-0.4.dist-info/WHEEL
KangRollGeneCancer-0.4.dist-info/top_level.txt
KangRollGeneCancer-0.4.dist-info/RECORD
