Metadata-Version: 2.1
Name: KangRollGeneCancer
Version: 0.4
Summary: xiaowenseekjob@gmail.com A brief description of Kang Roll package
Home-page: UNKNOWN
Author: Xiaowen kang
Author-email: UNKNOWN
License: UNKNOWN
Platform: UNKNOWN
